routers_package_grocom/__init__.py
routers_package_grocom/routers.py
routers_package_grocom-0.0.1.dist-info/LICENSE
routers_package_grocom-0.0.1.dist-info/METADATA
routers_package_grocom-0.0.1.dist-info/WHEEL
routers_package_grocom-0.0.1.dist-info/top_level.txt
routers_package_grocom-0.0.1.dist-info/RECORD
